utilspkg/__init__.py
utilspkg/utils_connections.py
utilspkg/utils_db.py
utilspkg/utils_email.py
utilspkg/utils_gpt.py
utilspkg/utils_init.py
utilspkg/utils_misc.py
utilspkg/utils_pta.py
utilspkg/utils_slack.py
utilspkg/utils_times.py
utilspkg-1.1.1.dist-info/METADATA
utilspkg-1.1.1.dist-info/WHEEL
utilspkg-1.1.1.dist-info/top_level.txt
utilspkg-1.1.1.dist-info/RECORD
