Metadata-Version: 2.1
Name: utilspkg
Version: 1.1.1
Requires-Dist: airtable-python-wrapper (>=0.15.3)
Requires-Dist: openai (>=0.27.7)
Requires-Dist: protobuf (>=4.24.1)
Requires-Dist: python-dotenv (>=1.0.0)
Requires-Dist: pytz (>=2023.3)
Requires-Dist: slack-sdk (>=3.21.3)
Requires-Dist: tenacity (>=8.2.2)
Requires-Dist: PyYAML
Requires-Dist: google-cloud-logging
